bakapi.py
bakapi-0.3.1.dist-info/licenses/LICENSE
bakapi-0.3.1.dist-info/METADATA
bakapi-0.3.1.dist-info/WHEEL
bakapi-0.3.1.dist-info/top_level.txt
bakapi-0.3.1.dist-info/RECORD
