Metadata-Version: 2.4
Name: bakapi
Version: 0.3.1
Summary: Bakaláři API v3 client
Home-page: https://github.com/mvolfik/bakapi
Author: Matěj Volf
Author-email: mat.volfik@gmail.com
License: MIT License
Project-URL: Documentation, https://github.com/mvolfik/bakapi/blob/master/README.md
Project-URL: Code, https://github.com/mvolfik/bakapi
Project-URL: Issue tracker, https://github.com/mvolfik/bakapi/issues
Classifier: Development Status :: 4 - Beta
Classifier: Intended Audience :: Developers
Classifier: License :: OSI Approved :: MIT License
Classifier: Natural Language :: Czech
Classifier: Operating System :: OS Independent
Classifier: Programming Language :: Python :: 3 :: Only
Classifier: Topic :: Education
Requires-Python: >=3.6
License-File: LICENSE
Requires-Dist: requests
Dynamic: author
Dynamic: author-email
Dynamic: classifier
Dynamic: description
Dynamic: description-content-type
Dynamic: home-page
Dynamic: license
Dynamic: license-file
Dynamic: project-url
Dynamic: requires-dist
Dynamic: requires-python
Dynamic: summary
